MANIFEST.in
README.rst
clj.py
setup.py
pyclj.egg-info/PKG-INFO
pyclj.egg-info/SOURCES.txt
pyclj.egg-info/dependency_links.txt
pyclj.egg-info/requires.txt
pyclj.egg-info/top_level.txt