Metadata-Version: 1.1
Name: pyclj
Version: 0.2.1
Summary: clojure literal reader and writer for python
Home-page: http://github.com/sunng87/pyclj
Author: Sun Ning
Author-email: sunng@about.me
License: mit
Platform: UNKNOWN
Classifier: Development Status :: 4 - Beta
Classifier: Intended Audience :: Developers
Classifier: License :: OSI Approved :: MIT License
Classifier: Topic :: Software Development
Classifier: Programming Language :: Python
Classifier: Operating System :: OS Independent
